fantraxapi/__init__.py
fantraxapi/api.py
fantraxapi/exceptions.py
fantraxapi/objs/__init__.py
fantraxapi/objs/base.py
fantraxapi/objs/game.py
fantraxapi/objs/league.py
fantraxapi/objs/player.py
fantraxapi/objs/position.py
fantraxapi/objs/roster.py
fantraxapi/objs/scoring_period.py
fantraxapi/objs/standings.py
fantraxapi/objs/status.py
fantraxapi/objs/team.py
fantraxapi/objs/trade.py
fantraxapi/objs/trade_block.py
fantraxapi/objs/transaction.py
fantraxapi-1.0.1.dist-info/licenses/LICENSE
fantraxapi-1.0.1.dist-info/METADATA
fantraxapi-1.0.1.dist-info/WHEEL
fantraxapi-1.0.1.dist-info/top_level.txt
fantraxapi-1.0.1.dist-info/RECORD
