Metadata-Version: 2.4
Name: fantraxapi
Version: 1.0.1
Summary: A lightweight Python library for The Fantrax API.
Home-page: https://github.com/meisnate12/FantraxAPI
Author: Nathan Taggart
Author-email: meisnate12@gmail.com
License: MIT License
Project-URL: Documentation, https://fantraxapi.kometa.wiki
Project-URL: Funding, https://github.com/sponsors/meisnate12
Project-URL: Source, https://github.com/meisnate12/FantraxAPI
Project-URL: Issues, https://github.com/meisnate12/FantraxAPI/issues
Keywords: fantraxapi,fantrax,fantasy,wrapper,api
Classifier: Development Status :: 5 - Production/Stable
Classifier: Intended Audience :: Developers
Classifier: Topic :: Software Development :: Libraries
Classifier: Programming Language :: Python
Classifier: Programming Language :: Python :: 3.11
Classifier: Programming Language :: Python :: 3.12
Classifier: Programming Language :: Python :: 3.13
Classifier: Programming Language :: Python :: 3.14
Requires-Python: >=3.11
License-File: LICENSE
Requires-Dist: requests
Requires-Dist: setuptools
Dynamic: author
Dynamic: author-email
Dynamic: classifier
Dynamic: description
Dynamic: description-content-type
Dynamic: home-page
Dynamic: keywords
Dynamic: license
Dynamic: license-file
Dynamic: project-url
Dynamic: requires-dist
Dynamic: requires-python
Dynamic: summary
